setup.py
mgamedev/__init__.py
mgamedev/test.py
mgamedev.egg-info/PKG-INFO
mgamedev.egg-info/SOURCES.txt
mgamedev.egg-info/dependency_links.txt
mgamedev.egg-info/top_level.txt
mgamedev/py_ex/__init__.py
mgamedev/py_ex/log_ex.py
mgamedev/py_ex/path_ex.py
mgamedev/py_ex/reader_ex.py
mgamedev/py_ex/writer_ex.py
mgamedev/py_lib/__init__.py
mgamedev/py_lib/colorlog.py
mgamedev/py_lib/decorator.py
mgamedev/py_lib/dhttp.py
mgamedev/py_lib/dutil.py
mgamedev/py_lib/luabase.py
mgamedev/py_lib/lupatool.py
mgamedev/py_lib/remote.py
mgamedev/py_lib/sqlitemgr.py
mgamedev/py_lib/xxtea.py
mgamedev/py_utils/__init__.py
mgamedev/py_utils/del_typefile.py
mgamedev/py_utils/dirtychk.py
mgamedev/py_utils/kill_process.py
mgamedev/texture/__init__.py
mgamedev/texture/cuptexture.py
mgamedev/texture/packsheet.py
mgamedev/texture/texture_png8.py
mgamedev/texture/texture_resize.py