Metadata-Version: 1.0
Name: mgamedev
Version: 0.1.8
Summary: Private tools for develop mobile client games
Home-page: https://gitee.com/heyzf/pytools_2dx
Author: dwb
Author-email: dwb@dwb.ren
License: Mozilla Licence
Keywords: dwb
Platform: UNKNOWN
